abckpi/__init__.py
abckpi/core.py
abckpi/utils.py
abckpi/tests/__init__.py
abckpi/tests/conftest.py
abckpi/tests/test_get_data.py
abckpi/tests/test_instance.py
abckpi/tests/test_set_data.py
python_abckpi-0.1.1.dist-info/LICENCE.md
python_abckpi-0.1.1.dist-info/METADATA
python_abckpi-0.1.1.dist-info/WHEEL
python_abckpi-0.1.1.dist-info/top_level.txt
python_abckpi-0.1.1.dist-info/RECORD
