Metadata-Version: 2.1
Name: python-abckpi
Version: 0.1.1
Summary: Python wrapper for the ABCKPI REST API
Home-page: https://gitlab.com/abckpi/python-abckpi/
Author: Seddik Yassine Abdelouadoud
Author-email: yassine@abckpi.com
License: The MIT License (MIT)
Platform: UNKNOWN
Classifier: License :: OSI Approved :: MIT License
Classifier: Programming Language :: Python :: 3
Classifier: Development Status :: 3 - Alpha
License-File: LICENCE.md
Requires-Dist: requests
